{
  "type": "betterwithaddons:mulberry",
  "version": 2,
  "ref": {
    "a": {
      "name": "betterwithaddons:leaves_mulberry",
      "meta": 0
    },
    "b": {
      "name": "betterwithaddons:log_mulberry",
      "meta": 4
    },
    "c": {
      "name": "betterwithaddons:leaves_mulberry",
      "meta": 2
    }
  },
  "shape": [
    [
      "     ",
      "     ",
      "accaa",
      "aaaac",
      "     ",
      "     "
    ],
    [
      "  a  ",
      " aa  ",
      "aaacc",
      "acaaa",
      "     ",
      "     "
    ],
    [
      " aac ",
      " cbc ",
      "aabcc",
      "aabac",
      "  b  ",
      "  b  "
    ],
    [
      "  a  ",
      "  a  ",
      "aacaa",
      "aaaaa",
      "     ",
      "     "
    ],
    [
      "     ",
      "     ",
      " aaa ",
      " aaa ",
      "     ",
      "     "
    ]
  ]
}
